[{"model": "project.kind", "pk": "60b041e4-8cea-4502-a61e-4d2879d2433f", "fields": {"order": 4, "name": "自主制作演劇企画", "symbol": "E", "food": "false", "slack_ch": "prj_engeki", "staff_list": []}}, {"model": "project.kind", "pk": "6c5dfe88-4cb4-44cb-9f13-a850664d804a", "fields": {"order": 3, "name": "グラウンド企画", "symbol": "G", "food": "false", "slack_ch": "prj_ground", "staff_list": []}}, {"model": "project.kind", "pk": "919129ec-f638-4403-a013-3a058141a435", "fields": {"order": 0, "name": "模擬店企画", "symbol": "M", "food": "true", "slack_ch": "prj_mogiten", "staff_list": []}}, {"model": "project.kind", "pk": "9f26d35d-b153-409a-b73b-da768566dd43", "fields": {"order": 1, "name": "ステージ企画", "symbol": "S", "food": "false", "slack_ch": "prj_stage", "staff_list": []}}, {"model": "project.kind", "pk": "f5a1c075-eac5-4491-9501-6dd0f430d829", "fields": {"order": 2, "name": "屋内企画", "symbol": "O", "food": "select", "slack_ch": "prj_okunai", "staff_list": []}}]